MANIFEST.in
README.md
requirements.txt
setup.py
vivarium_cell/__init__.py
vivarium_cell.egg-info/PKG-INFO
vivarium_cell.egg-info/SOURCES.txt
vivarium_cell.egg-info/dependency_links.txt
vivarium_cell.egg-info/entry_points.txt
vivarium_cell.egg-info/requires.txt
vivarium_cell.egg-info/top_level.txt
vivarium_cell/analysis/__init__.py
vivarium_cell/analysis/analyze.py
vivarium_cell/bigg_models/__init__.py
vivarium_cell/bigg_models/e_coli_core.json
vivarium_cell/bigg_models/iAF1260b.json
vivarium_cell/composites/__init__.py
vivarium_cell/composites/gene_expression.py
vivarium_cell/composites/growth_division.py
vivarium_cell/composites/growth_division_minimal.py
vivarium_cell/composites/inclusion_body_growth.py
vivarium_cell/composites/injected_glc_phosphorylation.py
vivarium_cell/composites/lattice.py
vivarium_cell/composites/master.py
vivarium_cell/composites/static_lattice.py
vivarium_cell/data/__init__.py
vivarium_cell/data/amino_acids.py
vivarium_cell/data/knowledge_base.py
vivarium_cell/data/molecular_weight.py
vivarium_cell/data/nucleotides.py
vivarium_cell/data/proteins.py
vivarium_cell/data/spreadsheets.py
vivarium_cell/data/synonyms.py
vivarium_cell/data/chromosomes/__init__.py
vivarium_cell/data/chromosomes/flagella_chromosome.py
vivarium_cell/data/chromosomes/gfp_chromosome.py
vivarium_cell/data/chromosomes/toy_chromosome.py
vivarium_cell/data/flat/Escherichia_coli_str_k_12_substr_mg1655.ASM584v2.dna.chromosome.Chromosome.fa
vivarium_cell/data/flat/__init__.py
vivarium_cell/data/flat/covert2002_GLC_G6P_flux_bounds.tsv
vivarium_cell/data/flat/covert2002_ecoli_metabolism_met_mw.tsv
vivarium_cell/data/flat/covert2002_exchange_fluxes.tsv
vivarium_cell/data/flat/covert2002_maintenance_biomass_fluxes.tsv
vivarium_cell/data/flat/covert2002_reactions.tsv
vivarium_cell/data/flat/covert2002_regulatory_proteins.tsv
vivarium_cell/data/flat/covert2002_transport.tsv
vivarium_cell/data/flat/lookup_conc_minimal.tsv
vivarium_cell/data/flat/lookup_conc_minimal_minus_oxygen.tsv
vivarium_cell/data/flat/lookup_conc_minimal_plus_amino_acids.tsv
vivarium_cell/data/flat/lookup_flux_minimal.tsv
vivarium_cell/data/flat/lookup_flux_minimal_minus_oxygen.tsv
