Metadata-Version: 2.1
Name: vivarium-cell
Version: 0.1.4
Summary: A collection of models for simulating cells with Vivarium.
Home-page: https://github.com/vivarium-collective/vivarium-cell
Author: Eran Agmon, Ryan Spangler
Author-email: eagmon@stanford.edu, ryan.spangler@gmail.com
License: MIT
Platform: UNKNOWN
